[
    {
        "title": "This is the title 1",
        "summary": "This is the document summary 1",
        "link": "This is the string for the document link"
    },
    {
        "title": "This is the title 2",
        "summary": "This is the document summary 2",
        "link": "This is the string for the document link"
    },
    {
        "title": "This is the title 3",
        "summary": "This is the document summary 3",
        "link": "This is the string for the document link"
    },
    {
        "title": "This is the title 4",
        "summary": "This is the document summary 4",
        "link": "This is the string for the document link"
    },
    {
        "title": "This is the title 5",
        "summary": "This is the document summary 5",
        "link": "This is the string for the document link"
    },
    {
        "title": "This is the title 6",
        "summary": "This is the document summary 6",
        "link": "This is the string for the document link"
    },
    {
        "title": "This is the title 7",
        "summary": "This is the document summary 7",
        "link": "This is the string for the document link"
    },
    {
        "title": "This is the title 8",
        "summary": "This is the document summary 8",
        "link": "This is the string for the document link"
    }
]